g2p_fa/__init__.py
g2p_fa/g2p_fa.py
g2p_fa/hparams.py
g2p_fa/model.py
g2p_fa/utils.py
g2p_fa/data/weights
g2p_fa-1.1.0.dist-info/LICENSE
g2p_fa-1.1.0.dist-info/METADATA
g2p_fa-1.1.0.dist-info/WHEEL
g2p_fa-1.1.0.dist-info/top_level.txt
g2p_fa-1.1.0.dist-info/RECORD
