Metadata-Version: 2.1
Name: g2p-fa
Version: 1.1.0
Summary: A Persian Grapheme to Phoneme model using LSTM implemented in pytorch
Home-page: https://github.com/de-mh/g2p_fa
Author: Mohamadhosein Dehghani
Author-email: demh1377@gmail.com
Classifier: Programming Language :: Python :: 3
Classifier: License :: OSI Approved :: MIT License
Classifier: Operating System :: OS Independent
Requires-Python: >=3.6
License-File: LICENSE
Requires-Dist: torch
